src/Growtopia/__init__.py
src/Growtopia/main.py
growtopiatools-1.0.dist-info/METADATA
growtopiatools-1.0.dist-info/WHEEL
growtopiatools-1.0.dist-info/licenses/LICENSE
growtopiatools-1.0.dist-info/RECORD
