Metadata-Version: 2.1
Name: GrowtopiaTools
Version: 1.0
Summary: Growtopia API
Project-URL: Homepage, https://growtopia.tools
Author-email: Bolwl <bolwlbusiness@gmail.com>
License-File: LICENSE
Classifier: License :: OSI Approved :: MIT License
Classifier: Operating System :: OS Independent
Classifier: Programming Language :: Python :: 3
Requires-Python: >=3.7
